tidyML/__init__.py
tidyML/dataMediator.py
tidyML/experimentTracker.py
tidyML/hyperparameterOptimizer.py
tidyML-0.6.8.dist-info/LICENSE
tidyML-0.6.8.dist-info/METADATA
tidyML-0.6.8.dist-info/WHEEL
tidyML-0.6.8.dist-info/top_level.txt
tidyML-0.6.8.dist-info/RECORD
