Metadata-Version: 2.1
Name: tidyML
Version: 0.6.8
Summary: Modularize your machine learning pipelines.
Home-page: https://github.com/finkbeiner-lab/tidyML
Author: Eric Mockler
Author-email: mock7ee@gmail.com
Project-URL: Bug Tracker, https://github.com/finkbeiner-lab/tidyML/issues
Classifier: Programming Language :: Python :: 3
Classifier: License :: OSI Approved :: MIT License
Classifier: Operating System :: OS Independent
Requires-Python: >=3.7
License-File: LICENSE
Requires-Dist: neptune-client
Requires-Dist: neptune-sklearn
Requires-Dist: numpy
Requires-Dist: pandas
Requires-Dist: scikit-learn
Requires-Dist: scikit-optimize
Requires-Dist: wandb
